fastapi_class/__init__.py
fastapi_class/logger.py
fastapi_class/openapi.py
fastapi_class/routers.py
fastapi_class/views.py
fastapi_class/exception/__init__.py
fastapi_class/exception/handler.py
fastapi_class-3.7.0.dist-info/METADATA
fastapi_class-3.7.0.dist-info/WHEEL
fastapi_class-3.7.0.dist-info/licenses/LICENSE
fastapi_class-3.7.0.dist-info/RECORD
